featureval/__init__.py
featureval/binning.py
featureval/metrics.py
featureval/preprocess.py
featureval/redrel.py
featureval/selection.py
feature_eval-0.0.13.dist-info/LICENSE
feature_eval-0.0.13.dist-info/METADATA
feature_eval-0.0.13.dist-info/WHEEL
feature_eval-0.0.13.dist-info/top_level.txt
feature_eval-0.0.13.dist-info/RECORD
