Metadata-Version: 2.1
Name: feature-eval
Version: 0.0.13
Summary: A user-friendly feature evaluation and selection package.
Author-email: Jingxiao Zhang <rex.zhang2016@foxmail.com>
Project-URL: Homepage, https://github.com/rexzhang2014/feature-eval
Project-URL: Bug Tracker, https://github.com/rexzhang2014/feature-eval/issues
Project-URL: Example Code, https://github.com/rexzhang2014/feature-eval/blob/master/tests/example.py
Classifier: Programming Language :: Python :: 3
Classifier: License :: OSI Approved :: MIT License
Classifier: Operating System :: OS Independent
Requires-Python: >=3.7
License-File: LICENSE
